vermils/__init__.py
vermils/asynctools/__init__.py
vermils/asynctools/asinkrunner.py
vermils/asynctools/tools.py
vermils/collections/__init__.py
vermils/collections/fridge.py
vermils/collections/objdict.py
vermils/collections/strchain.py
vermils/gadgets/__init__.py
vermils/gadgets/misc.py
vermils/gadgets/monologger.py
vermils/gadgets/sidelogging/__init__.py
vermils/io/__init__.py
vermils/io/aio/__init__.py
vermils/io/aio/atomic.py
vermils/io/aio/os.py
vermils/io/aio/path.py
vermils/io/aio/tempfile.py
vermils/io/aio/wrappers.py
vermils/io/atomic.py
vermils/io/misc.py
vermils/io/puller/__init__.py
vermils/io/puller/modifier.py
vermils/io/puller/pullers.py
vermils/py.typed
vermils/react/__init__.py
vermils/react/actionchain.py
vermils/react/eventhook.py
vermils/tensorflow/__init__.py
vermils/tensorflow/callbacks/__init__.py
vermils/tensorflow/inspect/__init__.py
vermils/tensorflow/layers/__init__.py
vermils/tensorflow/metrics/__init__.py
vermils/tensorflow/models/__init__.py
vermils-0.3.6.dist-info/LICENSE
vermils-0.3.6.dist-info/METADATA
vermils-0.3.6.dist-info/WHEEL
vermils-0.3.6.dist-info/RECORD
