Metadata-Version: 2.1
Name: vermils
Version: 0.3.6
Summary: 
Home-page: https://github.com/VermiIIi0n/VermilsMagicPocket
License: MIT
Keywords: utilities
Author: VermiIIi0n
Author-email: dungeon.behind0t@icloud.com
Requires-Python: >=3.10,<4.0
Classifier: Development Status :: 4 - Beta
Classifier: Framework :: Pytest
Classifier: Intended Audience :: Developers
Classifier: License :: OSI Approved :: MIT License
Classifier: Operating System :: OS Independent
Classifier: Programming Language :: Python :: 3
Classifier: Programming Language :: Python :: 3.10
Classifier: Programming Language :: Python :: 3.11
Classifier: Programming Language :: Python :: 3.12
Classifier: Programming Language :: Python :: Implementation :: CPython
Classifier: Programming Language :: Python :: Implementation :: PyPy
Classifier: Topic :: Utilities
Classifier: Typing :: Typed
Provides-Extra: all
Provides-Extra: http
Requires-Dist: httpx[http2,socks] (>=0.23.1,<0.24.0) ; extra == "http" or extra == "all"
Requires-Dist: nest-asyncio (>=1.5.6,<2.0.0)
Requires-Dist: rich (>=13.0.0,<14.0.0)
Project-URL: Issues, https://github.com/VermiIIi0n/VermilsMagicPocket/issues
